polar_diagrams/__init__.py
polar_diagrams/polar_diagrams.py
polar_diagrams-1.3.0.dist-info/LICENSE
polar_diagrams-1.3.0.dist-info/METADATA
polar_diagrams-1.3.0.dist-info/WHEEL
polar_diagrams-1.3.0.dist-info/top_level.txt
polar_diagrams-1.3.0.dist-info/RECORD
